alice/__init__.py
alice/__main__.py
alice_demo3-1.0.dist-info/DESCRIPTION.rst
alice_demo3-1.0.dist-info/METADATA
alice_demo3-1.0.dist-info/RECORD
alice_demo3-1.0.dist-info/WHEEL
alice_demo3-1.0.dist-info/metadata.json
alice_demo3-1.0.dist-info/top_level.txt
alice_package/__init__.py
foo_package/__init__.py
